pykdtree/__init__.py
pykdtree/kdtree.cpython-311-x86_64-linux-musl.so
pykdtree/kdtree.pyi
pykdtree/py.typed
pykdtree/render_template.py
pykdtree/test_stub.py
pykdtree/test_tree.py
pykdtree.libs/libgomp-8949ffbe.so.1.0.0
pykdtree-1.4.3.dist-info/METADATA
pykdtree-1.4.3.dist-info/WHEEL
pykdtree-1.4.3.dist-info/top_level.txt
pykdtree-1.4.3.dist-info/RECORD
pykdtree-1.4.3.dist-info/licenses/LICENSE.txt
