Metadata-Version: 2.4
Name: pykdtree
Version: 1.4.3
Summary: Fast kd-tree implementation with OpenMP-enabled queries
Home-page: https://github.com/storpipfugl/pykdtree
Author: Esben S. Nielsen
Author-email: storpipfugl@gmail.com
License: LGPL-3.0-or-later
Classifier: Development Status :: 5 - Production/Stable
Classifier: Programming Language :: Python
Classifier: Operating System :: OS Independent
Classifier: Intended Audience :: Science/Research
Classifier: Topic :: Scientific/Engineering
Classifier: Programming Language :: Python :: Free Threading :: 3 - Stable
Requires-Python: >=3.9
License-File: LICENSE.txt
Requires-Dist: numpy
Provides-Extra: test
Requires-Dist: pytest; extra == "test"
Requires-Dist: mypy; extra == "test"
Dynamic: author
Dynamic: author-email
Dynamic: classifier
Dynamic: description
Dynamic: description-content-type
Dynamic: home-page
Dynamic: license
Dynamic: license-file
Dynamic: provides-extra
Dynamic: requires-dist
Dynamic: requires-python
Dynamic: summary
